README.rst
setup.py
netconsole/__init__.py
netconsole/__main__.py
netconsole/_fakeds.py
netconsole/netconsole.py
netconsole/version.py
pynetconsole.egg-info/PKG-INFO
pynetconsole.egg-info/SOURCES.txt
pynetconsole.egg-info/dependency_links.txt
pynetconsole.egg-info/entry_points.txt
pynetconsole.egg-info/top_level.txt