Metadata-Version: 1.1
Name: pynetconsole
Version: 2.0.2
Summary: A pure python implementation of a NetConsole listener
Home-page: https://github.com/robotpy/pynetconsole
Author: RobotPy
Author-email: robotpy@googlegroups.com
License: ISC
Keywords: frc first robotics wpilib networktables
Platform: UNKNOWN
Classifier: Development Status :: 5 - Production/Stable
Classifier: Operating System :: OS Independent
Classifier: Environment :: Console
Classifier: Programming Language :: Python
Classifier: License :: OSI Approved :: ISC License (ISCL)
